tyler_python_helpers/__init__.py
tyler_python_helpers/chatgpt.py
tyler_python_helpers-0.1.2.dist-info/METADATA
tyler_python_helpers-0.1.2.dist-info/WHEEL
tyler_python_helpers-0.1.2.dist-info/entry_points.txt
tyler_python_helpers-0.1.2.dist-info/RECORD
